data_preprocessors/__init__.py
data_preprocessors/class_based_text_preprocessors.py
data_preprocessors/list_process.py
data_preprocessors/text_preprocessor.py
data_preprocessors-0.58.0.dist-info/METADATA
data_preprocessors-0.58.0.dist-info/WHEEL
data_preprocessors-0.58.0.dist-info/RECORD
