Metadata-Version: 2.1
Name: data-preprocessors
Version: 0.58.0
Summary: An easy to use tool for Data Preprocessing specially for Text Preprocessing
Home-page: https://github.com/MusfiqDehan/data-preprocessors
License: MIT
Keywords: nlp,data-preprocessors,data-preprocessing,text-preprocessing,data-science,textfile,musfiqdehan
Author: Md. Musfiqur Rahaman
Author-email: musfiqur.rahaman@northsouth.edu
Requires-Python: >=3.7.1,<4.0
Classifier: Development Status :: 5 - Production/Stable
Classifier: Intended Audience :: Developers
Classifier: Intended Audience :: Education
Classifier: Intended Audience :: Information Technology
Classifier: License :: OSI Approved :: MIT License
Classifier: Operating System :: OS Independent
Classifier: Programming Language :: Python :: 3
Classifier: Programming Language :: Python :: 3.8
Classifier: Programming Language :: Python :: 3.9
Classifier: Programming Language :: Python :: 3.10
Classifier: Programming Language :: Python :: 3.11
Classifier: Programming Language :: Python :: 3.12
Classifier: Topic :: Communications
Classifier: Topic :: Education
Classifier: Topic :: Software Development
Classifier: Topic :: Text Processing
Classifier: Topic :: Text Processing :: Linguistic
Requires-Dist: bnlp-toolkit (>=3.1.2,<4.0.0)
Requires-Dist: nltk (>=3.7,<4.0)
Requires-Dist: pandas (==1.3.0)
Project-URL: Repository, https://github.com/MusfiqDehan/data-preprocessors
